imgix/__init__.py
imgix/_version.py
imgix/compat.py
imgix/constants.py
imgix/errors.py
imgix/urlbuilder.py
imgix/urlhelper.py
imgix/validators.py
imgix-4.0.0.dist-info/AUTHORS.txt
imgix-4.0.0.dist-info/LICENSE
imgix-4.0.0.dist-info/METADATA
imgix-4.0.0.dist-info/WHEEL
imgix-4.0.0.dist-info/top_level.txt
imgix-4.0.0.dist-info/RECORD
